ruamel.std.argparse-0.8.1-py2.7-nspkg.pth
ruamel/std/argparse/__init__.py
ruamel/std/argparse/action/__init__.py
ruamel/std/argparse/action/checksinglestore.py
ruamel/std/argparse/action/count.py
ruamel/std/argparse/action/splitappend.py
ruamel.std.argparse-0.8.1.dist-info/DESCRIPTION.rst
ruamel.std.argparse-0.8.1.dist-info/LICENSE.txt
ruamel.std.argparse-0.8.1.dist-info/METADATA
ruamel.std.argparse-0.8.1.dist-info/RECORD
ruamel.std.argparse-0.8.1.dist-info/WHEEL
ruamel.std.argparse-0.8.1.dist-info/metadata.json
ruamel.std.argparse-0.8.1.dist-info/namespace_packages.txt
ruamel.std.argparse-0.8.1.dist-info/top_level.txt
