Metadata-Version: 1.1
Name: ruamel.std.argparse
Version: 0.8.1
Summary: Enhancements to argparse: extra actions, subparser aliases, smart formatter, a decorator based wrapper
Home-page: https://bitbucket.org/ruamel/std.argparse
Author: Anthon van der Neut
Author-email: a.van.der.neut@ruamel.eu
License: MIT license
Keywords: argparse enhanced
Platform: UNKNOWN
Classifier: Development Status :: 4 - Beta
Classifier: Intended Audience :: Developers
Classifier: License :: OSI Approved :: MIT License
Classifier: Operating System :: OS Independent
Classifier: Programming Language :: Python
